pydiffx/__init__.py
pydiffx/_version.py
pydiffx/errors.py
pydiffx/options.py
pydiffx/reader.py
pydiffx/sections.py
pydiffx/writer.py
pydiffx/dom/__init__.py
pydiffx/dom/objects.py
pydiffx/dom/properties.py
pydiffx/dom/reader.py
pydiffx/dom/writer.py
pydiffx/integrations/__init__.py
pydiffx/integrations/pygments_lexer.py
pydiffx/tests/__init__.py
pydiffx/tests/test_dom_objects.py
pydiffx/tests/test_reader.py
pydiffx/tests/test_utils_text.py
pydiffx/tests/test_utils_unified_diffs.py
pydiffx/tests/test_writer.py
pydiffx/tests/testcases.py
pydiffx/utils/__init__.py
pydiffx/utils/text.py
pydiffx/utils/unified_diffs.py
pydiffx-1.1.dist-info/AUTHORS
pydiffx-1.1.dist-info/LICENSE
pydiffx-1.1.dist-info/METADATA
pydiffx-1.1.dist-info/WHEEL
pydiffx-1.1.dist-info/entry_points.txt
pydiffx-1.1.dist-info/top_level.txt
pydiffx-1.1.dist-info/RECORD
