Metadata-Version: 2.1
Name: pydiffx
Version: 1.1
Summary: Python module for reading and writing DiffX files.
Home-page: https://diffx.org/pydiffx/
Author: Beanbag, Inc.
Author-email: questions@beanbaginc.com
Maintainer: Christian Hammond
Maintainer-email: christian@beanbaginc.com
License: MIT
Classifier: Development Status :: 5 - Production/Stable
Classifier: Environment :: Other Environment
Classifier: Intended Audience :: Developers
Classifier: License :: OSI Approved :: MIT License
Classifier: Natural Language :: English
Classifier: Operating System :: OS Independent
Classifier: Programming Language :: Python
Classifier: Programming Language :: Python :: 2
Classifier: Programming Language :: Python :: 2.7
Classifier: Programming Language :: Python :: 3
Classifier: Programming Language :: Python :: 3.6
Classifier: Programming Language :: Python :: 3.7
Classifier: Programming Language :: Python :: 3.8
Classifier: Programming Language :: Python :: 3.9
Classifier: Programming Language :: Python :: 3.10
Classifier: Programming Language :: Python :: 3.11
Classifier: Topic :: Software Development
Classifier: Topic :: Software Development :: Libraries :: Python Modules
Classifier: Topic :: Software Development :: Version Control
Classifier: Topic :: Text Processing
Classifier: Topic :: Text Processing :: General
License-File: LICENSE
License-File: AUTHORS
Requires-Dist: six
